{"numTotalTestSuites":7,"numPassedTestSuites":4,"numFailedTestSuites":3,"numPendingTestSuites":0,"numTotalTests":60,"numPassedTests":60,"numFailedTests":0,"numPendingTests":0,"numTodoTests":0,"snapshot":{"added":0,"failure":false,"filesAdded":0,"filesRemoved":0,"filesRemovedList":[],"filesUnmatched":0,"filesUpdated":0,"matched":0,"total":0,"unchecked":0,"uncheckedKeysByFile":[],"unmatched":0,"updated":0,"didUpdate":false},"startTime":1773620180992,"success":false,"testResults":[{"assertionResults":[],"startTime":1773620180992,"endTime":1773620180992,"status":"failed","message":"Parse failure: Expected '{', got 'let'\nAt file: /ex-01-variaveis-nomes.js:91:7","name":"/home/vicmca/CodeProjects/School/materiais/atividades/3d-rev-01/ex01.test.js"},{"assertionResults":[],"startTime":1773620180992,"endTime":1773620180992,"status":"failed","message":"Parse failure: Expression expected\nAt file: /ex-02-variaveis-tipos.js:44:0","name":"/home/vicmca/CodeProjects/School/materiais/atividades/3d-rev-01/ex02.test.js"},{"assertionResults":[{"ancestorTitles":["Exercício 03"],"fullName":"Exercício 03 ex03 - Válida - Questão 1","status":"passed","title":"ex03 - Válida - Questão 1","duration":4.997491000000082,"failureMessages":[],"meta":{}},{"ancestorTitles":["Exercício 03"],"fullName":"Exercício 03 ex03 - Correta - Questão 1","status":"passed","title":"ex03 - Correta - Questão 1","duration":0.8156000000000176,"failureMessages":[],"meta":{}},{"ancestorTitles":["Exercício 03"],"fullName":"Exercício 03 ex03 - Válida - Questão 2","status":"passed","title":"ex03 - Válida - Questão 2","duration":0.5817830000000868,"failureMessages":[],"meta":{}},{"ancestorTitles":["Exercício 03"],"fullName":"Exercício 03 ex03 - Correta - Questão 2","status":"passed","title":"ex03 - Correta - Questão 2","duration":1.0120200000000068,"failureMessages":[],"meta":{}},{"ancestorTitles":["Exercício 03"],"fullName":"Exercício 03 ex03 - Válida - Questão 3","status":"passed","title":"ex03 - Válida - Questão 3","duration":0.6605270000000019,"failureMessages":[],"meta":{}},{"ancestorTitles":["Exercício 03"],"fullName":"Exercício 03 ex03 - Correta - Questão 3","status":"passed","title":"ex03 - Correta - Questão 3","duration":0.3865610000000288,"failureMessages":[],"meta":{}},{"ancestorTitles":["Exercício 03"],"fullName":"Exercício 03 ex03 - Válida - Questão 4","status":"passed","title":"ex03 - Válida - Questão 4","duration":0.8468110000000024,"failureMessages":[],"meta":{}},{"ancestorTitles":["Exercício 03"],"fullName":"Exercício 03 ex03 - Correta - Questão 4","status":"passed","title":"ex03 - Correta - Questão 4","duration":0.41196000000002186,"failureMessages":[],"meta":{}},{"ancestorTitles":["Exercício 03"],"fullName":"Exercício 03 ex03 - Válida - Questão 5","status":"passed","title":"ex03 - Válida - Questão 5","duration":1.272087000000056,"failureMessages":[],"meta":{}},{"ancestorTitles":["Exercício 03"],"fullName":"Exercício 03 ex03 - Correta - Questão 5","status":"passed","title":"ex03 - Correta - Questão 5","duration":0.5106150000000298,"failureMessages":[],"meta":{}},{"ancestorTitles":["Exercício 03"],"fullName":"Exercício 03 ex03 - Válida - Questão 6","status":"passed","title":"ex03 - Válida - Questão 6","duration":0.4053589999999758,"failureMessages":[],"meta":{}},{"ancestorTitles":["Exercício 03"],"fullName":"Exercício 03 ex03 - Correta - Questão 6","status":"passed","title":"ex03 - Correta - Questão 6","duration":0.2807949999998982,"failureMessages":[],"meta":{}},{"ancestorTitles":["Exercício 03"],"fullName":"Exercício 03 ex03 - Válida - Questão 7","status":"passed","title":"ex03 - Válida - Questão 7","duration":0.3785059999999021,"failureMessages":[],"meta":{}},{"ancestorTitles":["Exercício 03"],"fullName":"Exercício 03 ex03 - Correta - Questão 7","status":"passed","title":"ex03 - Correta - Questão 7","duration":0.2739930000000186,"failureMessages":[],"meta":{}},{"ancestorTitles":["Exercício 03"],"fullName":"Exercício 03 ex03 - Válida - Questão 8","status":"passed","title":"ex03 - Válida - Questão 8","duration":0.3934830000000602,"failureMessages":[],"meta":{}},{"ancestorTitles":["Exercício 03"],"fullName":"Exercício 03 ex03 - Correta - Questão 8","status":"passed","title":"ex03 - Correta - Questão 8","duration":0.26637000000005173,"failureMessages":[],"meta":{}},{"ancestorTitles":["Exercício 03"],"fullName":"Exercício 03 ex03 - Válida - Questão 9","status":"passed","title":"ex03 - Válida - Questão 9","duration":0.5822819999999638,"failureMessages":[],"meta":{}},{"ancestorTitles":["Exercício 03"],"fullName":"Exercício 03 ex03 - Correta - Questão 9","status":"passed","title":"ex03 - Correta - Questão 9","duration":0.2854849999999942,"failureMessages":[],"meta":{}},{"ancestorTitles":["Exercício 03"],"fullName":"Exercício 03 ex03 - Válida - Questão 10","status":"passed","title":"ex03 - Válida - Questão 10","duration":0.41304600000000846,"failureMessages":[],"meta":{}},{"ancestorTitles":["Exercício 03"],"fullName":"Exercício 03 ex03 - Correta - Questão 10","status":"passed","title":"ex03 - Correta - Questão 10","duration":0.3101080000000138,"failureMessages":[],"meta":{}}],"startTime":1773620182776,"endTime":1773620182793.413,"status":"passed","message":"","name":"/home/vicmca/CodeProjects/School/materiais/atividades/3d-rev-01/ex03.test.js"},{"assertionResults":[{"ancestorTitles":["Exercício 04"],"fullName":"Exercício 04 ex04 - Válida - Questão 1","status":"passed","title":"ex04 - Válida - Questão 1","duration":20.996659000000136,"failureMessages":[],"meta":{}},{"ancestorTitles":["Exercício 04"],"fullName":"Exercício 04 ex04 - Correta - Questão 1","status":"passed","title":"ex04 - Correta - Questão 1","duration":0.903814999999895,"failureMessages":[],"meta":{}},{"ancestorTitles":["Exercício 04"],"fullName":"Exercício 04 ex04 - Válida - Questão 2","status":"passed","title":"ex04 - Válida - Questão 2","duration":8.056635999999799,"failureMessages":[],"meta":{}},{"ancestorTitles":["Exercício 04"],"fullName":"Exercício 04 ex04 - Correta - Questão 2","status":"passed","title":"ex04 - Correta - Questão 2","duration":1.216673000000128,"failureMessages":[],"meta":{}},{"ancestorTitles":["Exercício 04"],"fullName":"Exercício 04 ex04 - Válida - Questão 3","status":"passed","title":"ex04 - Válida - Questão 3","duration":0.7138509999999769,"failureMessages":[],"meta":{}},{"ancestorTitles":["Exercício 04"],"fullName":"Exercício 04 ex04 - Correta - Questão 3","status":"passed","title":"ex04 - Correta - Questão 3","duration":0.5468019999998432,"failureMessages":[],"meta":{}},{"ancestorTitles":["Exercício 04"],"fullName":"Exercício 04 ex04 - Válida - Questão 4","status":"passed","title":"ex04 - Válida - Questão 4","duration":1.0017640000000938,"failureMessages":[],"meta":{}},{"ancestorTitles":["Exercício 04"],"fullName":"Exercício 04 ex04 - Correta - Questão 4","status":"passed","title":"ex04 - Correta - Questão 4","duration":0.4513719999999921,"failureMessages":[],"meta":{}},{"ancestorTitles":["Exercício 04"],"fullName":"Exercício 04 ex04 - Válida - Questão 5","status":"passed","title":"ex04 - Válida - Questão 5","duration":5.507199000000128,"failureMessages":[],"meta":{}},{"ancestorTitles":["Exercício 04"],"fullName":"Exercício 04 ex04 - Correta - Questão 5","status":"passed","title":"ex04 - Correta - Questão 5","duration":0.6237189999999373,"failureMessages":[],"meta":{}},{"ancestorTitles":["Exercício 04"],"fullName":"Exercício 04 ex04 - Válida - Questão 6","status":"passed","title":"ex04 - Válida - Questão 6","duration":0.4523340000000644,"failureMessages":[],"meta":{}},{"ancestorTitles":["Exercício 04"],"fullName":"Exercício 04 ex04 - Correta - Questão 6","status":"passed","title":"ex04 - Correta - Questão 6","duration":0.2663400000001275,"failureMessages":[],"meta":{}},{"ancestorTitles":["Exercício 04"],"fullName":"Exercício 04 ex04 - Válida - Questão 7","status":"passed","title":"ex04 - Válida - Questão 7","duration":0.36882300000002033,"failureMessages":[],"meta":{}},{"ancestorTitles":["Exercício 04"],"fullName":"Exercício 04 ex04 - Correta - Questão 7","status":"passed","title":"ex04 - Correta - Questão 7","duration":0.26049799999987044,"failureMessages":[],"meta":{}},{"ancestorTitles":["Exercício 04"],"fullName":"Exercício 04 ex04 - Válida - Questão 8","status":"passed","title":"ex04 - Válida - Questão 8","duration":0.46378200000003744,"failureMessages":[],"meta":{}},{"ancestorTitles":["Exercício 04"],"fullName":"Exercício 04 ex04 - Correta - Questão 8","status":"passed","title":"ex04 - Correta - Questão 8","duration":0.29864199999997254,"failureMessages":[],"meta":{}},{"ancestorTitles":["Exercício 04"],"fullName":"Exercício 04 ex04 - Válida - Questão 9","status":"passed","title":"ex04 - Válida - Questão 9","duration":4.221045000000004,"failureMessages":[],"meta":{}},{"ancestorTitles":["Exercício 04"],"fullName":"Exercício 04 ex04 - Correta - Questão 9","status":"passed","title":"ex04 - Correta - Questão 9","duration":0.3443090000000666,"failureMessages":[],"meta":{}},{"ancestorTitles":["Exercício 04"],"fullName":"Exercício 04 ex04 - Válida - Questão 10","status":"passed","title":"ex04 - Válida - Questão 10","duration":0.44952699999998913,"failureMessages":[],"meta":{}},{"ancestorTitles":["Exercício 04"],"fullName":"Exercício 04 ex04 - Correta - Questão 10","status":"passed","title":"ex04 - Correta - Questão 10","duration":0.3434030000000803,"failureMessages":[],"meta":{}},{"ancestorTitles":["Exercício 04"],"fullName":"Exercício 04 ex04 - Válida - Questão 11","status":"passed","title":"ex04 - Válida - Questão 11","duration":0.4187249999999949,"failureMessages":[],"meta":{}},{"ancestorTitles":["Exercício 04"],"fullName":"Exercício 04 ex04 - Correta - Questão 11","status":"passed","title":"ex04 - Correta - Questão 11","duration":0.31684100000006765,"failureMessages":[],"meta":{}},{"ancestorTitles":["Exercício 04"],"fullName":"Exercício 04 ex04 - Válida - Questão 12","status":"passed","title":"ex04 - Válida - Questão 12","duration":0.40280299999994895,"failureMessages":[],"meta":{}},{"ancestorTitles":["Exercício 04"],"fullName":"Exercício 04 ex04 - Correta - Questão 12","status":"passed","title":"ex04 - Correta - Questão 12","duration":0.2791949999998451,"failureMessages":[],"meta":{}},{"ancestorTitles":["Exercício 04"],"fullName":"Exercício 04 ex04 - Válida - Questão 13","status":"passed","title":"ex04 - Válida - Questão 13","duration":0.382720000000063,"failureMessages":[],"meta":{}},{"ancestorTitles":["Exercício 04"],"fullName":"Exercício 04 ex04 - Correta - Questão 13","status":"passed","title":"ex04 - Correta - Questão 13","duration":0.39507000000003245,"failureMessages":[],"meta":{}},{"ancestorTitles":["Exercício 04"],"fullName":"Exercício 04 ex04 - Válida - Questão 14","status":"passed","title":"ex04 - Válida - Questão 14","duration":0.45728399999984504,"failureMessages":[],"meta":{}},{"ancestorTitles":["Exercício 04"],"fullName":"Exercício 04 ex04 - Correta - Questão 14","status":"passed","title":"ex04 - Correta - Questão 14","duration":0.2788299999999708,"failureMessages":[],"meta":{}},{"ancestorTitles":["Exercício 04"],"fullName":"Exercício 04 ex04 - Válida - Questão 15","status":"passed","title":"ex04 - Válida - Questão 15","duration":0.3806889999998475,"failureMessages":[],"meta":{}},{"ancestorTitles":["Exercício 04"],"fullName":"Exercício 04 ex04 - Correta - Questão 15","status":"passed","title":"ex04 - Correta - Questão 15","duration":0.2753810000001522,"failureMessages":[],"meta":{}},{"ancestorTitles":["Exercício 04"],"fullName":"Exercício 04 ex04 - Válida - Questão 16","status":"passed","title":"ex04 - Válida - Questão 16","duration":0.6318469999998797,"failureMessages":[],"meta":{}},{"ancestorTitles":["Exercício 04"],"fullName":"Exercício 04 ex04 - Correta - Questão 16","status":"passed","title":"ex04 - Correta - Questão 16","duration":0.28993000000014035,"failureMessages":[],"meta":{}},{"ancestorTitles":["Exercício 04"],"fullName":"Exercício 04 ex04 - Válida - Questão 17","status":"passed","title":"ex04 - Válida - Questão 17","duration":0.3670150000000376,"failureMessages":[],"meta":{}},{"ancestorTitles":["Exercício 04"],"fullName":"Exercício 04 ex04 - Correta - Questão 17","status":"passed","title":"ex04 - Correta - Questão 17","duration":0.2531429999999091,"failureMessages":[],"meta":{}},{"ancestorTitles":["Exercício 04"],"fullName":"Exercício 04 ex04 - Válida - Questão 18","status":"passed","title":"ex04 - Válida - Questão 18","duration":0.3517810000000736,"failureMessages":[],"meta":{}},{"ancestorTitles":["Exercício 04"],"fullName":"Exercício 04 ex04 - Correta - Questão 18","status":"passed","title":"ex04 - Correta - Questão 18","duration":0.25684400000000096,"failureMessages":[],"meta":{}},{"ancestorTitles":["Exercício 04"],"fullName":"Exercício 04 ex04 - Válida - Questão 19","status":"passed","title":"ex04 - Válida - Questão 19","duration":0.5250590000000557,"failureMessages":[],"meta":{}},{"ancestorTitles":["Exercício 04"],"fullName":"Exercício 04 ex04 - Correta - Questão 19","status":"passed","title":"ex04 - Correta - Questão 19","duration":0.3000770000001012,"failureMessages":[],"meta":{}},{"ancestorTitles":["Exercício 04"],"fullName":"Exercício 04 ex04 - Válida - Questão 20","status":"passed","title":"ex04 - Válida - Questão 20","duration":0.3902069999999185,"failureMessages":[],"meta":{}},{"ancestorTitles":["Exercício 04"],"fullName":"Exercício 04 ex04 - Correta - Questão 20","status":"passed","title":"ex04 - Correta - Questão 20","duration":0.27656200000001263,"failureMessages":[],"meta":{}}],"startTime":1773620182130,"endTime":1773620182194.2766,"status":"passed","message":"","name":"/home/vicmca/CodeProjects/School/materiais/atividades/3d-rev-01/ex04.test.js"},{"assertionResults":[],"startTime":1773620180992,"endTime":1773620180992,"status":"failed","message":"Parse failure: The left-hand side of an assignment expression must be a variable or a property access.\nAt file: /ex-05-operadores-logicos.js:73:26","name":"/home/vicmca/CodeProjects/School/materiais/atividades/3d-rev-01/ex05.test.js"}]}