{"numTotalTestSuites":10,"numPassedTestSuites":4,"numFailedTestSuites":6,"numPendingTestSuites":0,"numTotalTests":160,"numPassedTests":152,"numFailedTests":8,"numPendingTests":0,"numTodoTests":0,"snapshot":{"added":0,"failure":false,"filesAdded":0,"filesRemoved":0,"filesRemovedList":[],"filesUnmatched":0,"filesUpdated":0,"matched":0,"total":0,"unchecked":0,"uncheckedKeysByFile":[],"unmatched":0,"updated":0,"didUpdate":false},"startTime":1773070760765,"success":false,"testResults":[{"assertionResults":[{"ancestorTitles":["Exercício 01"],"fullName":"Exercício 01 Ex01 - Válida - Questão 1","status":"passed","title":"Ex01 - Válida - Questão 1","duration":6.304099000000065,"failureMessages":[],"meta":{}},{"ancestorTitles":["Exercício 01"],"fullName":"Exercício 01 Ex01 - Correta - Questão 1","status":"passed","title":"Ex01 - Correta - Questão 1","duration":0.964277999999922,"failureMessages":[],"meta":{}},{"ancestorTitles":["Exercício 01"],"fullName":"Exercício 01 Ex01 - Válida - Questão 2","status":"passed","title":"Ex01 - Válida - Questão 2","duration":0.6400380000000041,"failureMessages":[],"meta":{}},{"ancestorTitles":["Exercício 01"],"fullName":"Exercício 01 Ex01 - Correta - Questão 2","status":"passed","title":"Ex01 - Correta - Questão 2","duration":1.2480669999999918,"failureMessages":[],"meta":{}},{"ancestorTitles":["Exercício 01"],"fullName":"Exercício 01 Ex01 - Válida - Questão 3","status":"passed","title":"Ex01 - Válida - Questão 3","duration":0.6994320000000016,"failureMessages":[],"meta":{}},{"ancestorTitles":["Exercício 01"],"fullName":"Exercício 01 Ex01 - Correta - Questão 3","status":"passed","title":"Ex01 - Correta - Questão 3","duration":0.44811600000002727,"failureMessages":[],"meta":{}},{"ancestorTitles":["Exercício 01"],"fullName":"Exercício 01 Ex01 - Válida - Questão 4","status":"failed","title":"Ex01 - Válida - Questão 4","duration":26.99954200000002,"failureMessages":["AssertionError: expected undefined to be type of 'boolean'\n    at /home/vicmca/CodeProjects/School/materiais/atividades/3d-rev-01/ex01.test.js:24:30\n    at file:///home/vicmca/CodeProjects/School/materiais/atividades/3d-rev-01/node_modules/@vitest/runner/dist/index.js:145:11\n    at file:///home/vicmca/CodeProjects/School/materiais/atividades/3d-rev-01/node_modules/@vitest/runner/dist/index.js:915:26\n    at file:///home/vicmca/CodeProjects/School/materiais/atividades/3d-rev-01/node_modules/@vitest/runner/dist/index.js:1243:20\n    at new Promise (<anonymous>)\n    at runWithTimeout (file:///home/vicmca/CodeProjects/School/materiais/atividades/3d-rev-01/node_modules/@vitest/runner/dist/index.js:1209:10)\n    at file:///home/vicmca/CodeProjects/School/materiais/atividades/3d-rev-01/node_modules/@vitest/runner/dist/index.js:1653:37\n    at Traces.$ (file:///home/vicmca/CodeProjects/School/materiais/atividades/3d-rev-01/node_modules/vitest/dist/chunks/traces.CCmnQaNT.js:142:27)\n    at trace (file:///home/vicmca/CodeProjects/School/materiais/atividades/3d-rev-01/node_modules/vitest/dist/chunks/test.B8ej_ZHS.js:239:21)\n    at runTest (file:///home/vicmca/CodeProjects/School/materiais/atividades/3d-rev-01/node_modules/@vitest/runner/dist/index.js:1653:12)"],"meta":{}},{"ancestorTitles":["Exercício 01"],"fullName":"Exercício 01 Ex01 - Correta - Questão 4","status":"failed","title":"Ex01 - Correta - Questão 4","duration":3.810632999999939,"failureMessages":["AssertionError: expected undefined to be type of 'boolean'\n    at /home/vicmca/CodeProjects/School/materiais/atividades/3d-rev-01/ex01.test.js:28:30\n    at file:///home/vicmca/CodeProjects/School/materiais/atividades/3d-rev-01/node_modules/@vitest/runner/dist/index.js:145:11\n    at file:///home/vicmca/CodeProjects/School/materiais/atividades/3d-rev-01/node_modules/@vitest/runner/dist/index.js:915:26\n    at file:///home/vicmca/CodeProjects/School/materiais/atividades/3d-rev-01/node_modules/@vitest/runner/dist/index.js:1243:20\n    at new Promise (<anonymous>)\n    at runWithTimeout (file:///home/vicmca/CodeProjects/School/materiais/atividades/3d-rev-01/node_modules/@vitest/runner/dist/index.js:1209:10)\n    at file:///home/vicmca/CodeProjects/School/materiais/atividades/3d-rev-01/node_modules/@vitest/runner/dist/index.js:1653:37\n    at Traces.$ (file:///home/vicmca/CodeProjects/School/materiais/atividades/3d-rev-01/node_modules/vitest/dist/chunks/traces.CCmnQaNT.js:142:27)\n    at trace (file:///home/vicmca/CodeProjects/School/materiais/atividades/3d-rev-01/node_modules/vitest/dist/chunks/test.B8ej_ZHS.js:239:21)\n    at runTest (file:///home/vicmca/CodeProjects/School/materiais/atividades/3d-rev-01/node_modules/@vitest/runner/dist/index.js:1653:12)"],"meta":{}},{"ancestorTitles":["Exercício 01"],"fullName":"Exercício 01 Ex01 - Válida - Questão 5","status":"passed","title":"Ex01 - Válida - Questão 5","duration":2.6492090000000417,"failureMessages":[],"meta":{}},{"ancestorTitles":["Exercício 01"],"fullName":"Exercício 01 Ex01 - Correta - Questão 5","status":"passed","title":"Ex01 - Correta - Questão 5","duration":0.6085599999998976,"failureMessages":[],"meta":{}},{"ancestorTitles":["Exercício 01"],"fullName":"Exercício 01 Ex01 - Válida - Questão 6","status":"passed","title":"Ex01 - Válida - Questão 6","duration":0.4907869999999548,"failureMessages":[],"meta":{}},{"ancestorTitles":["Exercício 01"],"fullName":"Exercício 01 Ex01 - Correta - Questão 6","status":"passed","title":"Ex01 - Correta - Questão 6","duration":0.26860499999997955,"failureMessages":[],"meta":{}},{"ancestorTitles":["Exercício 01"],"fullName":"Exercício 01 Ex01 - Válida - Questão 7","status":"passed","title":"Ex01 - Válida - Questão 7","duration":0.26167900000007194,"failureMessages":[],"meta":{}},{"ancestorTitles":["Exercício 01"],"fullName":"Exercício 01 Ex01 - Correta - Questão 7","status":"passed","title":"Ex01 - Correta - Questão 7","duration":0.18077499999992597,"failureMessages":[],"meta":{}},{"ancestorTitles":["Exercício 01"],"fullName":"Exercício 01 Ex01 - Válida - Questão 8","status":"passed","title":"Ex01 - Válida - Questão 8","duration":0.23275599999999486,"failureMessages":[],"meta":{}},{"ancestorTitles":["Exercício 01"],"fullName":"Exercício 01 Ex01 - Correta - Questão 8","status":"passed","title":"Ex01 - Correta - Questão 8","duration":0.18389799999999923,"failureMessages":[],"meta":{}},{"ancestorTitles":["Exercício 01"],"fullName":"Exercício 01 Ex01 - Válida - Questão 9","status":"passed","title":"Ex01 - Válida - Questão 9","duration":0.21634900000003654,"failureMessages":[],"meta":{}},{"ancestorTitles":["Exercício 01"],"fullName":"Exercício 01 Ex01 - Correta - Questão 9","status":"passed","title":"Ex01 - Correta - Questão 9","duration":0.18192999999996573,"failureMessages":[],"meta":{}},{"ancestorTitles":["Exercício 01"],"fullName":"Exercício 01 Ex01 - Válida - Questão 10","status":"failed","title":"Ex01 - Válida - Questão 10","duration":3.4182510000000548,"failureMessages":["AssertionError: expected undefined to be type of 'boolean'\n    at /home/vicmca/CodeProjects/School/materiais/atividades/3d-rev-01/ex01.test.js:24:30\n    at file:///home/vicmca/CodeProjects/School/materiais/atividades/3d-rev-01/node_modules/@vitest/runner/dist/index.js:145:11\n    at file:///home/vicmca/CodeProjects/School/materiais/atividades/3d-rev-01/node_modules/@vitest/runner/dist/index.js:915:26\n    at file:///home/vicmca/CodeProjects/School/materiais/atividades/3d-rev-01/node_modules/@vitest/runner/dist/index.js:1243:20\n    at new Promise (<anonymous>)\n    at runWithTimeout (file:///home/vicmca/CodeProjects/School/materiais/atividades/3d-rev-01/node_modules/@vitest/runner/dist/index.js:1209:10)\n    at file:///home/vicmca/CodeProjects/School/materiais/atividades/3d-rev-01/node_modules/@vitest/runner/dist/index.js:1653:37\n    at Traces.$ (file:///home/vicmca/CodeProjects/School/materiais/atividades/3d-rev-01/node_modules/vitest/dist/chunks/traces.CCmnQaNT.js:142:27)\n    at trace (file:///home/vicmca/CodeProjects/School/materiais/atividades/3d-rev-01/node_modules/vitest/dist/chunks/test.B8ej_ZHS.js:239:21)\n    at runTest (file:///home/vicmca/CodeProjects/School/materiais/atividades/3d-rev-01/node_modules/@vitest/runner/dist/index.js:1653:12)"],"meta":{}},{"ancestorTitles":["Exercício 01"],"fullName":"Exercício 01 Ex01 - Correta - Questão 10","status":"failed","title":"Ex01 - Correta - Questão 10","duration":4.661775000000034,"failureMessages":["AssertionError: expected undefined to be type of 'boolean'\n    at /home/vicmca/CodeProjects/School/materiais/atividades/3d-rev-01/ex01.test.js:28:30\n    at file:///home/vicmca/CodeProjects/School/materiais/atividades/3d-rev-01/node_modules/@vitest/runner/dist/index.js:145:11\n    at file:///home/vicmca/CodeProjects/School/materiais/atividades/3d-rev-01/node_modules/@vitest/runner/dist/index.js:915:26\n    at file:///home/vicmca/CodeProjects/School/materiais/atividades/3d-rev-01/node_modules/@vitest/runner/dist/index.js:1243:20\n    at new Promise (<anonymous>)\n    at runWithTimeout (file:///home/vicmca/CodeProjects/School/materiais/atividades/3d-rev-01/node_modules/@vitest/runner/dist/index.js:1209:10)\n    at file:///home/vicmca/CodeProjects/School/materiais/atividades/3d-rev-01/node_modules/@vitest/runner/dist/index.js:1653:37\n    at Traces.$ (file:///home/vicmca/CodeProjects/School/materiais/atividades/3d-rev-01/node_modules/vitest/dist/chunks/traces.CCmnQaNT.js:142:27)\n    at trace (file:///home/vicmca/CodeProjects/School/materiais/atividades/3d-rev-01/node_modules/vitest/dist/chunks/test.B8ej_ZHS.js:239:21)\n    at runTest (file:///home/vicmca/CodeProjects/School/materiais/atividades/3d-rev-01/node_modules/@vitest/runner/dist/index.js:1653:12)"],"meta":{}},{"ancestorTitles":["Exercício 01"],"fullName":"Exercício 01 Ex01 - Válida - Questão 11","status":"passed","title":"Ex01 - Válida - Questão 11","duration":0.42650900000001,"failureMessages":[],"meta":{}},{"ancestorTitles":["Exercício 01"],"fullName":"Exercício 01 Ex01 - Correta - Questão 11","status":"passed","title":"Ex01 - Correta - Questão 11","duration":0.3171710000000303,"failureMessages":[],"meta":{}},{"ancestorTitles":["Exercício 01"],"fullName":"Exercício 01 Ex01 - Válida - Questão 12","status":"passed","title":"Ex01 - Válida - Questão 12","duration":0.4362820000000056,"failureMessages":[],"meta":{}},{"ancestorTitles":["Exercício 01"],"fullName":"Exercício 01 Ex01 - Correta - Questão 12","status":"passed","title":"Ex01 - Correta - Questão 12","duration":0.20466399999997975,"failureMessages":[],"meta":{}},{"ancestorTitles":["Exercício 01"],"fullName":"Exercício 01 Ex01 - Válida - Questão 13","status":"passed","title":"Ex01 - Válida - Questão 13","duration":0.2509340000000293,"failureMessages":[],"meta":{}},{"ancestorTitles":["Exercício 01"],"fullName":"Exercício 01 Ex01 - Correta - Questão 13","status":"passed","title":"Ex01 - Correta - Questão 13","duration":0.17648799999994935,"failureMessages":[],"meta":{}},{"ancestorTitles":["Exercício 01"],"fullName":"Exercício 01 Ex01 - Válida - Questão 14","status":"passed","title":"Ex01 - Válida - Questão 14","duration":0.2581959999999981,"failureMessages":[],"meta":{}},{"ancestorTitles":["Exercício 01"],"fullName":"Exercício 01 Ex01 - Correta - Questão 14","status":"passed","title":"Ex01 - Correta - Questão 14","duration":0.23977700000000368,"failureMessages":[],"meta":{}},{"ancestorTitles":["Exercício 01"],"fullName":"Exercício 01 Ex01 - Válida - Questão 15","status":"passed","title":"Ex01 - Válida - Questão 15","duration":0.7965850000000501,"failureMessages":[],"meta":{}},{"ancestorTitles":["Exercício 01"],"fullName":"Exercício 01 Ex01 - Correta - Questão 15","status":"passed","title":"Ex01 - Correta - Questão 15","duration":1.2168920000000298,"failureMessages":[],"meta":{}},{"ancestorTitles":["Exercício 01"],"fullName":"Exercício 01 Ex01 - Válida - Questão 16","status":"passed","title":"Ex01 - Válida - Questão 16","duration":0.7671569999999974,"failureMessages":[],"meta":{}},{"ancestorTitles":["Exercício 01"],"fullName":"Exercício 01 Ex01 - Correta - Questão 16","status":"passed","title":"Ex01 - Correta - Questão 16","duration":0.43754599999999755,"failureMessages":[],"meta":{}},{"ancestorTitles":["Exercício 01"],"fullName":"Exercício 01 Ex01 - Válida - Questão 17","status":"failed","title":"Ex01 - Válida - Questão 17","duration":2.8339260000000195,"failureMessages":["AssertionError: expected undefined to be type of 'boolean'\n    at /home/vicmca/CodeProjects/School/materiais/atividades/3d-rev-01/ex01.test.js:24:30\n    at file:///home/vicmca/CodeProjects/School/materiais/atividades/3d-rev-01/node_modules/@vitest/runner/dist/index.js:145:11\n    at file:///home/vicmca/CodeProjects/School/materiais/atividades/3d-rev-01/node_modules/@vitest/runner/dist/index.js:915:26\n    at file:///home/vicmca/CodeProjects/School/materiais/atividades/3d-rev-01/node_modules/@vitest/runner/dist/index.js:1243:20\n    at new Promise (<anonymous>)\n    at runWithTimeout (file:///home/vicmca/CodeProjects/School/materiais/atividades/3d-rev-01/node_modules/@vitest/runner/dist/index.js:1209:10)\n    at file:///home/vicmca/CodeProjects/School/materiais/atividades/3d-rev-01/node_modules/@vitest/runner/dist/index.js:1653:37\n    at Traces.$ (file:///home/vicmca/CodeProjects/School/materiais/atividades/3d-rev-01/node_modules/vitest/dist/chunks/traces.CCmnQaNT.js:142:27)\n    at trace (file:///home/vicmca/CodeProjects/School/materiais/atividades/3d-rev-01/node_modules/vitest/dist/chunks/test.B8ej_ZHS.js:239:21)\n    at runTest (file:///home/vicmca/CodeProjects/School/materiais/atividades/3d-rev-01/node_modules/@vitest/runner/dist/index.js:1653:12)"],"meta":{}},{"ancestorTitles":["Exercício 01"],"fullName":"Exercício 01 Ex01 - Correta - Questão 17","status":"failed","title":"Ex01 - Correta - Questão 17","duration":2.577338999999938,"failureMessages":["AssertionError: expected undefined to be type of 'boolean'\n    at /home/vicmca/CodeProjects/School/materiais/atividades/3d-rev-01/ex01.test.js:28:30\n    at file:///home/vicmca/CodeProjects/School/materiais/atividades/3d-rev-01/node_modules/@vitest/runner/dist/index.js:145:11\n    at file:///home/vicmca/CodeProjects/School/materiais/atividades/3d-rev-01/node_modules/@vitest/runner/dist/index.js:915:26\n    at file:///home/vicmca/CodeProjects/School/materiais/atividades/3d-rev-01/node_modules/@vitest/runner/dist/index.js:1243:20\n    at new Promise (<anonymous>)\n    at runWithTimeout (file:///home/vicmca/CodeProjects/School/materiais/atividades/3d-rev-01/node_modules/@vitest/runner/dist/index.js:1209:10)\n    at file:///home/vicmca/CodeProjects/School/materiais/atividades/3d-rev-01/node_modules/@vitest/runner/dist/index.js:1653:37\n    at Traces.$ (file:///home/vicmca/CodeProjects/School/materiais/atividades/3d-rev-01/node_modules/vitest/dist/chunks/traces.CCmnQaNT.js:142:27)\n    at trace (file:///home/vicmca/CodeProjects/School/materiais/atividades/3d-rev-01/node_modules/vitest/dist/chunks/test.B8ej_ZHS.js:239:21)\n    at runTest (file:///home/vicmca/CodeProjects/School/materiais/atividades/3d-rev-01/node_modules/@vitest/runner/dist/index.js:1653:12)"],"meta":{}},{"ancestorTitles":["Exercício 01"],"fullName":"Exercício 01 Ex01 - Válida - Questão 18","status":"passed","title":"Ex01 - Válida - Questão 18","duration":0.5045800000000327,"failureMessages":[],"meta":{}},{"ancestorTitles":["Exercício 01"],"fullName":"Exercício 01 Ex01 - Correta - Questão 18","status":"passed","title":"Ex01 - Correta - Questão 18","duration":0.38159799999993993,"failureMessages":[],"meta":{}},{"ancestorTitles":["Exercício 01"],"fullName":"Exercício 01 Ex01 - Válida - Questão 19","status":"passed","title":"Ex01 - Válida - Questão 19","duration":0.4364739999999756,"failureMessages":[],"meta":{}},{"ancestorTitles":["Exercício 01"],"fullName":"Exercício 01 Ex01 - Correta - Questão 19","status":"passed","title":"Ex01 - Correta - Questão 19","duration":0.2720839999999498,"failureMessages":[],"meta":{}},{"ancestorTitles":["Exercício 01"],"fullName":"Exercício 01 Ex01 - Válida - Questão 20","status":"passed","title":"Ex01 - Válida - Questão 20","duration":0.25111299999991843,"failureMessages":[],"meta":{}},{"ancestorTitles":["Exercício 01"],"fullName":"Exercício 01 Ex01 - Correta - Questão 20","status":"passed","title":"Ex01 - Correta - Questão 20","duration":0.18343000000004395,"failureMessages":[],"meta":{}}],"startTime":1773070761530,"endTime":1773070761600.272,"status":"failed","message":"","name":"/home/vicmca/CodeProjects/School/materiais/atividades/3d-rev-01/ex01.test.js"},{"assertionResults":[{"ancestorTitles":["Exercício 02"],"fullName":"Exercício 02 Ex02 - Válida - Questão 1","status":"passed","title":"Ex02 - Válida - Questão 1","duration":4.814597999999933,"failureMessages":[],"meta":{}},{"ancestorTitles":["Exercício 02"],"fullName":"Exercício 02 Ex02 - Correta - Questão 1","status":"passed","title":"Ex02 - Correta - Questão 1","duration":0.8888699999999972,"failureMessages":[],"meta":{}},{"ancestorTitles":["Exercício 02"],"fullName":"Exercício 02 Ex02 - Válida - Questão 2","status":"failed","title":"Ex02 - Válida - Questão 2","duration":24.72656900000004,"failureMessages":["AssertionError: expected 'Mesa' to be type of 'object'\n    at /home/vicmca/CodeProjects/School/materiais/atividades/3d-rev-01/ex02.test.js:25:30\n    at file:///home/vicmca/CodeProjects/School/materiais/atividades/3d-rev-01/node_modules/@vitest/runner/dist/index.js:145:11\n    at file:///home/vicmca/CodeProjects/School/materiais/atividades/3d-rev-01/node_modules/@vitest/runner/dist/index.js:915:26\n    at file:///home/vicmca/CodeProjects/School/materiais/atividades/3d-rev-01/node_modules/@vitest/runner/dist/index.js:1243:20\n    at new Promise (<anonymous>)\n    at runWithTimeout (file:///home/vicmca/CodeProjects/School/materiais/atividades/3d-rev-01/node_modules/@vitest/runner/dist/index.js:1209:10)\n    at file:///home/vicmca/CodeProjects/School/materiais/atividades/3d-rev-01/node_modules/@vitest/runner/dist/index.js:1653:37\n    at Traces.$ (file:///home/vicmca/CodeProjects/School/materiais/atividades/3d-rev-01/node_modules/vitest/dist/chunks/traces.CCmnQaNT.js:142:27)\n    at trace (file:///home/vicmca/CodeProjects/School/materiais/atividades/3d-rev-01/node_modules/vitest/dist/chunks/test.B8ej_ZHS.js:239:21)\n    at runTest (file:///home/vicmca/CodeProjects/School/materiais/atividades/3d-rev-01/node_modules/@vitest/runner/dist/index.js:1653:12)"],"meta":{}},{"ancestorTitles":["Exercício 02"],"fullName":"Exercício 02 Ex02 - Correta - Questão 2","status":"passed","title":"Ex02 - Correta - Questão 2","duration":0.6873959999999215,"failureMessages":[],"meta":{}},{"ancestorTitles":["Exercício 02"],"fullName":"Exercício 02 Ex02 - Válida - Questão 3","status":"passed","title":"Ex02 - Válida - Questão 3","duration":0.5768390000000636,"failureMessages":[],"meta":{}},{"ancestorTitles":["Exercício 02"],"fullName":"Exercício 02 Ex02 - Correta - Questão 3","status":"passed","title":"Ex02 - Correta - Questão 3","duration":0.6447050000000445,"failureMessages":[],"meta":{}},{"ancestorTitles":["Exercício 02"],"fullName":"Exercício 02 Ex02 - Válida - Questão 4","status":"passed","title":"Ex02 - Válida - Questão 4","duration":0.9285109999999577,"failureMessages":[],"meta":{}},{"ancestorTitles":["Exercício 02"],"fullName":"Exercício 02 Ex02 - Correta - Questão 4","status":"passed","title":"Ex02 - Correta - Questão 4","duration":0.4466620000000603,"failureMessages":[],"meta":{}},{"ancestorTitles":["Exercício 02"],"fullName":"Exercício 02 Ex02 - Válida - Questão 5","status":"passed","title":"Ex02 - Válida - Questão 5","duration":1.2489060000000336,"failureMessages":[],"meta":{}},{"ancestorTitles":["Exercício 02"],"fullName":"Exercício 02 Ex02 - Correta - Questão 5","status":"passed","title":"Ex02 - Correta - Questão 5","duration":0.8381539999999177,"failureMessages":[],"meta":{}},{"ancestorTitles":["Exercício 02"],"fullName":"Exercício 02 Ex02 - Válida - Questão 6","status":"passed","title":"Ex02 - Válida - Questão 6","duration":0.5163079999999809,"failureMessages":[],"meta":{}},{"ancestorTitles":["Exercício 02"],"fullName":"Exercício 02 Ex02 - Correta - Questão 6","status":"passed","title":"Ex02 - Correta - Questão 6","duration":0.30971599999998034,"failureMessages":[],"meta":{}},{"ancestorTitles":["Exercício 02"],"fullName":"Exercício 02 Ex02 - Válida - Questão 7","status":"passed","title":"Ex02 - Válida - Questão 7","duration":0.5230209999999715,"failureMessages":[],"meta":{}},{"ancestorTitles":["Exercício 02"],"fullName":"Exercício 02 Ex02 - Correta - Questão 7","status":"passed","title":"Ex02 - Correta - Questão 7","duration":0.3346490000000131,"failureMessages":[],"meta":{}},{"ancestorTitles":["Exercício 02"],"fullName":"Exercício 02 Ex02 - Válida - Questão 8","status":"passed","title":"Ex02 - Válida - Questão 8","duration":0.4691409999999223,"failureMessages":[],"meta":{}},{"ancestorTitles":["Exercício 02"],"fullName":"Exercício 02 Ex02 - Correta - Questão 8","status":"passed","title":"Ex02 - Correta - Questão 8","duration":0.295880000000011,"failureMessages":[],"meta":{}},{"ancestorTitles":["Exercício 02"],"fullName":"Exercício 02 Ex02 - Válida - Questão 9","status":"passed","title":"Ex02 - Válida - Questão 9","duration":0.3943859999999404,"failureMessages":[],"meta":{}},{"ancestorTitles":["Exercício 02"],"fullName":"Exercício 02 Ex02 - Correta - Questão 9","status":"passed","title":"Ex02 - Correta - Questão 9","duration":0.2866820000000416,"failureMessages":[],"meta":{}},{"ancestorTitles":["Exercício 02"],"fullName":"Exercício 02 Ex02 - Válida - Questão 10","status":"passed","title":"Ex02 - Válida - Questão 10","duration":0.8483800000000201,"failureMessages":[],"meta":{}},{"ancestorTitles":["Exercício 02"],"fullName":"Exercício 02 Ex02 - Correta - Questão 10","status":"passed","title":"Ex02 - Correta - Questão 10","duration":0.3811279999999897,"failureMessages":[],"meta":{}},{"ancestorTitles":["Exercício 02"],"fullName":"Exercício 02 Ex02 - Válida - Questão 11","status":"passed","title":"Ex02 - Válida - Questão 11","duration":0.43679199999996854,"failureMessages":[],"meta":{}},{"ancestorTitles":["Exercício 02"],"fullName":"Exercício 02 Ex02 - Correta - Questão 11","status":"passed","title":"Ex02 - Correta - Questão 11","duration":0.19974300000001222,"failureMessages":[],"meta":{}},{"ancestorTitles":["Exercício 02"],"fullName":"Exercício 02 Ex02 - Válida - Questão 12","status":"passed","title":"Ex02 - Válida - Questão 12","duration":0.27455799999995634,"failureMessages":[],"meta":{}},{"ancestorTitles":["Exercício 02"],"fullName":"Exercício 02 Ex02 - Correta - Questão 12","status":"passed","title":"Ex02 - Correta - Questão 12","duration":0.1821830000000091,"failureMessages":[],"meta":{}},{"ancestorTitles":["Exercício 02"],"fullName":"Exercício 02 Ex02 - Válida - Questão 13","status":"passed","title":"Ex02 - Válida - Questão 13","duration":0.2310090000000855,"failureMessages":[],"meta":{}},{"ancestorTitles":["Exercício 02"],"fullName":"Exercício 02 Ex02 - Correta - Questão 13","status":"passed","title":"Ex02 - Correta - Questão 13","duration":0.1741869999999608,"failureMessages":[],"meta":{}},{"ancestorTitles":["Exercício 02"],"fullName":"Exercício 02 Ex02 - Válida - Questão 14","status":"passed","title":"Ex02 - Válida - Questão 14","duration":0.3426240000000007,"failureMessages":[],"meta":{}},{"ancestorTitles":["Exercício 02"],"fullName":"Exercício 02 Ex02 - Correta - Questão 14","status":"passed","title":"Ex02 - Correta - Questão 14","duration":0.25955799999997,"failureMessages":[],"meta":{}},{"ancestorTitles":["Exercício 02"],"fullName":"Exercício 02 Ex02 - Válida - Questão 15","status":"passed","title":"Ex02 - Válida - Questão 15","duration":0.37480200000004515,"failureMessages":[],"meta":{}},{"ancestorTitles":["Exercício 02"],"fullName":"Exercício 02 Ex02 - Correta - Questão 15","status":"passed","title":"Ex02 - Correta - Questão 15","duration":0.26187900000002173,"failureMessages":[],"meta":{}},{"ancestorTitles":["Exercício 02"],"fullName":"Exercício 02 Ex02 - Válida - Questão 16","status":"passed","title":"Ex02 - Válida - Questão 16","duration":0.39899800000000596,"failureMessages":[],"meta":{}},{"ancestorTitles":["Exercício 02"],"fullName":"Exercício 02 Ex02 - Correta - Questão 16","status":"passed","title":"Ex02 - Correta - Questão 16","duration":0.48255300000005263,"failureMessages":[],"meta":{}},{"ancestorTitles":["Exercício 02"],"fullName":"Exercício 02 Ex02 - Válida - Questão 17","status":"passed","title":"Ex02 - Válida - Questão 17","duration":0.39168500000005224,"failureMessages":[],"meta":{}},{"ancestorTitles":["Exercício 02"],"fullName":"Exercício 02 Ex02 - Correta - Questão 17","status":"passed","title":"Ex02 - Correta - Questão 17","duration":0.26178200000003926,"failureMessages":[],"meta":{}},{"ancestorTitles":["Exercício 02"],"fullName":"Exercício 02 Ex02 - Válida - Questão 18","status":"passed","title":"Ex02 - Válida - Questão 18","duration":0.37635999999997694,"failureMessages":[],"meta":{}},{"ancestorTitles":["Exercício 02"],"fullName":"Exercício 02 Ex02 - Correta - Questão 18","status":"passed","title":"Ex02 - Correta - Questão 18","duration":0.27234999999996035,"failureMessages":[],"meta":{}},{"ancestorTitles":["Exercício 02"],"fullName":"Exercício 02 Ex02 - Válida - Questão 19","status":"passed","title":"Ex02 - Válida - Questão 19","duration":0.36529300000006515,"failureMessages":[],"meta":{}},{"ancestorTitles":["Exercício 02"],"fullName":"Exercício 02 Ex02 - Correta - Questão 19","status":"passed","title":"Ex02 - Correta - Questão 19","duration":0.26280100000008133,"failureMessages":[],"meta":{}},{"ancestorTitles":["Exercício 02"],"fullName":"Exercício 02 Ex02 - Válida - Questão 20","status":"passed","title":"Ex02 - Válida - Questão 20","duration":0.37492199999996956,"failureMessages":[],"meta":{}},{"ancestorTitles":["Exercício 02"],"fullName":"Exercício 02 Ex02 - Correta - Questão 20","status":"passed","title":"Ex02 - Correta - Questão 20","duration":0.25981899999999314,"failureMessages":[],"meta":{}}],"startTime":1773070761601,"endTime":1773070761650.375,"status":"failed","message":"","name":"/home/vicmca/CodeProjects/School/materiais/atividades/3d-rev-01/ex02.test.js"},{"assertionResults":[{"ancestorTitles":["Exercício 03"],"fullName":"Exercício 03 ex03 - Válida - Questão 1","status":"passed","title":"ex03 - Válida - Questão 1","duration":2.510005000000092,"failureMessages":[],"meta":{}},{"ancestorTitles":["Exercício 03"],"fullName":"Exercício 03 ex03 - Correta - Questão 1","status":"passed","title":"ex03 - Correta - Questão 1","duration":0.4370850000000246,"failureMessages":[],"meta":{}},{"ancestorTitles":["Exercício 03"],"fullName":"Exercício 03 ex03 - Válida - Questão 2","status":"passed","title":"ex03 - Válida - Questão 2","duration":0.3075770000000375,"failureMessages":[],"meta":{}},{"ancestorTitles":["Exercício 03"],"fullName":"Exercício 03 ex03 - Correta - Questão 2","status":"passed","title":"ex03 - Correta - Questão 2","duration":0.5997240000000374,"failureMessages":[],"meta":{}},{"ancestorTitles":["Exercício 03"],"fullName":"Exercício 03 ex03 - Válida - Questão 3","status":"passed","title":"ex03 - Válida - Questão 3","duration":0.4832539999999881,"failureMessages":[],"meta":{}},{"ancestorTitles":["Exercício 03"],"fullName":"Exercício 03 ex03 - Correta - Questão 3","status":"passed","title":"ex03 - Correta - Questão 3","duration":0.278144999999995,"failureMessages":[],"meta":{}},{"ancestorTitles":["Exercício 03"],"fullName":"Exercício 03 ex03 - Válida - Questão 4","status":"passed","title":"ex03 - Válida - Questão 4","duration":1.6896050000000287,"failureMessages":[],"meta":{}},{"ancestorTitles":["Exercício 03"],"fullName":"Exercício 03 ex03 - Correta - Questão 4","status":"passed","title":"ex03 - Correta - Questão 4","duration":0.3400259999999662,"failureMessages":[],"meta":{}},{"ancestorTitles":["Exercício 03"],"fullName":"Exercício 03 ex03 - Válida - Questão 5","status":"passed","title":"ex03 - Válida - Questão 5","duration":0.8401479999999992,"failureMessages":[],"meta":{}},{"ancestorTitles":["Exercício 03"],"fullName":"Exercício 03 ex03 - Correta - Questão 5","status":"passed","title":"ex03 - Correta - Questão 5","duration":0.32579600000008213,"failureMessages":[],"meta":{}},{"ancestorTitles":["Exercício 03"],"fullName":"Exercício 03 ex03 - Válida - Questão 6","status":"passed","title":"ex03 - Válida - Questão 6","duration":0.2335130000000163,"failureMessages":[],"meta":{}},{"ancestorTitles":["Exercício 03"],"fullName":"Exercício 03 ex03 - Correta - Questão 6","status":"passed","title":"ex03 - Correta - Questão 6","duration":0.1569250000000011,"failureMessages":[],"meta":{}},{"ancestorTitles":["Exercício 03"],"fullName":"Exercício 03 ex03 - Válida - Questão 7","status":"passed","title":"ex03 - Válida - Questão 7","duration":0.2933610000000044,"failureMessages":[],"meta":{}},{"ancestorTitles":["Exercício 03"],"fullName":"Exercício 03 ex03 - Correta - Questão 7","status":"passed","title":"ex03 - Correta - Questão 7","duration":0.22075899999992998,"failureMessages":[],"meta":{}},{"ancestorTitles":["Exercício 03"],"fullName":"Exercício 03 ex03 - Válida - Questão 8","status":"passed","title":"ex03 - Válida - Questão 8","duration":0.30654500000002827,"failureMessages":[],"meta":{}},{"ancestorTitles":["Exercício 03"],"fullName":"Exercício 03 ex03 - Correta - Questão 8","status":"passed","title":"ex03 - Correta - Questão 8","duration":0.20085200000005443,"failureMessages":[],"meta":{}},{"ancestorTitles":["Exercício 03"],"fullName":"Exercício 03 ex03 - Válida - Questão 9","status":"passed","title":"ex03 - Válida - Questão 9","duration":0.4685069999999314,"failureMessages":[],"meta":{}},{"ancestorTitles":["Exercício 03"],"fullName":"Exercício 03 ex03 - Correta - Questão 9","status":"passed","title":"ex03 - Correta - Questão 9","duration":0.15064299999994546,"failureMessages":[],"meta":{}},{"ancestorTitles":["Exercício 03"],"fullName":"Exercício 03 ex03 - Válida - Questão 10","status":"passed","title":"ex03 - Válida - Questão 10","duration":0.2223989999999958,"failureMessages":[],"meta":{}},{"ancestorTitles":["Exercício 03"],"fullName":"Exercício 03 ex03 - Correta - Questão 10","status":"passed","title":"ex03 - Correta - Questão 10","duration":0.14540099999999256,"failureMessages":[],"meta":{}}],"startTime":1773070762201,"endTime":1773070762213.1455,"status":"passed","message":"","name":"/home/vicmca/CodeProjects/School/materiais/atividades/3d-rev-01/ex03.test.js"},{"assertionResults":[{"ancestorTitles":["Exercício 04"],"fullName":"Exercício 04 ex04 - Válida - Questão 1","status":"passed","title":"ex04 - Válida - Questão 1","duration":2.5857389999999896,"failureMessages":[],"meta":{}},{"ancestorTitles":["Exercício 04"],"fullName":"Exercício 04 ex04 - Correta - Questão 1","status":"passed","title":"ex04 - Correta - Questão 1","duration":0.4680150000000367,"failureMessages":[],"meta":{}},{"ancestorTitles":["Exercício 04"],"fullName":"Exercício 04 ex04 - Válida - Questão 2","status":"passed","title":"ex04 - Válida - Questão 2","duration":0.32514900000001035,"failureMessages":[],"meta":{}},{"ancestorTitles":["Exercício 04"],"fullName":"Exercício 04 ex04 - Correta - Questão 2","status":"passed","title":"ex04 - Correta - Questão 2","duration":0.5554049999999506,"failureMessages":[],"meta":{}},{"ancestorTitles":["Exercício 04"],"fullName":"Exercício 04 ex04 - Válida - Questão 3","status":"passed","title":"ex04 - Válida - Questão 3","duration":0.3724650000000338,"failureMessages":[],"meta":{}},{"ancestorTitles":["Exercício 04"],"fullName":"Exercício 04 ex04 - Correta - Questão 3","status":"passed","title":"ex04 - Correta - Questão 3","duration":0.21596199999999044,"failureMessages":[],"meta":{}},{"ancestorTitles":["Exercício 04"],"fullName":"Exercício 04 ex04 - Válida - Questão 4","status":"passed","title":"ex04 - Válida - Questão 4","duration":0.47565399999996316,"failureMessages":[],"meta":{}},{"ancestorTitles":["Exercício 04"],"fullName":"Exercício 04 ex04 - Correta - Questão 4","status":"passed","title":"ex04 - Correta - Questão 4","duration":0.2262230000000045,"failureMessages":[],"meta":{}},{"ancestorTitles":["Exercício 04"],"fullName":"Exercício 04 ex04 - Válida - Questão 5","status":"passed","title":"ex04 - Válida - Questão 5","duration":0.6417380000000321,"failureMessages":[],"meta":{}},{"ancestorTitles":["Exercício 04"],"fullName":"Exercício 04 ex04 - Correta - Questão 5","status":"passed","title":"ex04 - Correta - Questão 5","duration":0.2731059999999843,"failureMessages":[],"meta":{}},{"ancestorTitles":["Exercício 04"],"fullName":"Exercício 04 ex04 - Válida - Questão 6","status":"passed","title":"ex04 - Válida - Questão 6","duration":0.21566600000005565,"failureMessages":[],"meta":{}},{"ancestorTitles":["Exercício 04"],"fullName":"Exercício 04 ex04 - Correta - Questão 6","status":"passed","title":"ex04 - Correta - Questão 6","duration":0.12976800000001276,"failureMessages":[],"meta":{}},{"ancestorTitles":["Exercício 04"],"fullName":"Exercício 04 ex04 - Válida - Questão 7","status":"passed","title":"ex04 - Válida - Questão 7","duration":0.21270700000002307,"failureMessages":[],"meta":{}},{"ancestorTitles":["Exercício 04"],"fullName":"Exercício 04 ex04 - Correta - Questão 7","status":"passed","title":"ex04 - Correta - Questão 7","duration":0.1198219999999992,"failureMessages":[],"meta":{}},{"ancestorTitles":["Exercício 04"],"fullName":"Exercício 04 ex04 - Válida - Questão 8","status":"passed","title":"ex04 - Válida - Questão 8","duration":0.18088999999997668,"failureMessages":[],"meta":{}},{"ancestorTitles":["Exercício 04"],"fullName":"Exercício 04 ex04 - Correta - Questão 8","status":"passed","title":"ex04 - Correta - Questão 8","duration":0.11617999999998574,"failureMessages":[],"meta":{}},{"ancestorTitles":["Exercício 04"],"fullName":"Exercício 04 ex04 - Válida - Questão 9","status":"passed","title":"ex04 - Válida - Questão 9","duration":0.3110350000000608,"failureMessages":[],"meta":{}},{"ancestorTitles":["Exercício 04"],"fullName":"Exercício 04 ex04 - Correta - Questão 9","status":"passed","title":"ex04 - Correta - Questão 9","duration":0.13351399999999103,"failureMessages":[],"meta":{}},{"ancestorTitles":["Exercício 04"],"fullName":"Exercício 04 ex04 - Válida - Questão 10","status":"passed","title":"ex04 - Válida - Questão 10","duration":0.18871999999998934,"failureMessages":[],"meta":{}},{"ancestorTitles":["Exercício 04"],"fullName":"Exercício 04 ex04 - Correta - Questão 10","status":"passed","title":"ex04 - Correta - Questão 10","duration":0.12595299999998133,"failureMessages":[],"meta":{}},{"ancestorTitles":["Exercício 04"],"fullName":"Exercício 04 ex04 - Válida - Questão 11","status":"passed","title":"ex04 - Válida - Questão 11","duration":0.17342599999994945,"failureMessages":[],"meta":{}},{"ancestorTitles":["Exercício 04"],"fullName":"Exercício 04 ex04 - Correta - Questão 11","status":"passed","title":"ex04 - Correta - Questão 11","duration":0.1193789999999808,"failureMessages":[],"meta":{}},{"ancestorTitles":["Exercício 04"],"fullName":"Exercício 04 ex04 - Válida - Questão 12","status":"passed","title":"ex04 - Válida - Questão 12","duration":0.1626379999999017,"failureMessages":[],"meta":{}},{"ancestorTitles":["Exercício 04"],"fullName":"Exercício 04 ex04 - Correta - Questão 12","status":"passed","title":"ex04 - Correta - Questão 12","duration":0.11600499999997282,"failureMessages":[],"meta":{}},{"ancestorTitles":["Exercício 04"],"fullName":"Exercício 04 ex04 - Válida - Questão 13","status":"passed","title":"ex04 - Válida - Questão 13","duration":0.1636389999999892,"failureMessages":[],"meta":{}},{"ancestorTitles":["Exercício 04"],"fullName":"Exercício 04 ex04 - Correta - Questão 13","status":"passed","title":"ex04 - Correta - Questão 13","duration":0.1084929999999531,"failureMessages":[],"meta":{}},{"ancestorTitles":["Exercício 04"],"fullName":"Exercício 04 ex04 - Válida - Questão 14","status":"passed","title":"ex04 - Válida - Questão 14","duration":0.16121099999998023,"failureMessages":[],"meta":{}},{"ancestorTitles":["Exercício 04"],"fullName":"Exercício 04 ex04 - Correta - Questão 14","status":"passed","title":"ex04 - Correta - Questão 14","duration":0.10881299999994098,"failureMessages":[],"meta":{}},{"ancestorTitles":["Exercício 04"],"fullName":"Exercício 04 ex04 - Válida - Questão 15","status":"passed","title":"ex04 - Válida - Questão 15","duration":0.15689300000008188,"failureMessages":[],"meta":{}},{"ancestorTitles":["Exercício 04"],"fullName":"Exercício 04 ex04 - Correta - Questão 15","status":"passed","title":"ex04 - Correta - Questão 15","duration":0.13767999999993208,"failureMessages":[],"meta":{}},{"ancestorTitles":["Exercício 04"],"fullName":"Exercício 04 ex04 - Válida - Questão 16","status":"passed","title":"ex04 - Válida - Questão 16","duration":0.2617329999999356,"failureMessages":[],"meta":{}},{"ancestorTitles":["Exercício 04"],"fullName":"Exercício 04 ex04 - Correta - Questão 16","status":"passed","title":"ex04 - Correta - Questão 16","duration":0.11765700000000834,"failureMessages":[],"meta":{}},{"ancestorTitles":["Exercício 04"],"fullName":"Exercício 04 ex04 - Válida - Questão 17","status":"passed","title":"ex04 - Válida - Questão 17","duration":0.19068300000003546,"failureMessages":[],"meta":{}},{"ancestorTitles":["Exercício 04"],"fullName":"Exercício 04 ex04 - Correta - Questão 17","status":"passed","title":"ex04 - Correta - Questão 17","duration":0.15327400000001035,"failureMessages":[],"meta":{}},{"ancestorTitles":["Exercício 04"],"fullName":"Exercício 04 ex04 - Válida - Questão 18","status":"passed","title":"ex04 - Válida - Questão 18","duration":0.2229300000000194,"failureMessages":[],"meta":{}},{"ancestorTitles":["Exercício 04"],"fullName":"Exercício 04 ex04 - Correta - Questão 18","status":"passed","title":"ex04 - Correta - Questão 18","duration":0.15649299999995492,"failureMessages":[],"meta":{}},{"ancestorTitles":["Exercício 04"],"fullName":"Exercício 04 ex04 - Válida - Questão 19","status":"passed","title":"ex04 - Válida - Questão 19","duration":0.2281590000000051,"failureMessages":[],"meta":{}},{"ancestorTitles":["Exercício 04"],"fullName":"Exercício 04 ex04 - Correta - Questão 19","status":"passed","title":"ex04 - Correta - Questão 19","duration":0.11117699999999786,"failureMessages":[],"meta":{}},{"ancestorTitles":["Exercício 04"],"fullName":"Exercício 04 ex04 - Válida - Questão 20","status":"passed","title":"ex04 - Válida - Questão 20","duration":0.16654400000004443,"failureMessages":[],"meta":{}},{"ancestorTitles":["Exercício 04"],"fullName":"Exercício 04 ex04 - Correta - Questão 20","status":"passed","title":"ex04 - Correta - Questão 20","duration":0.1855440000000499,"failureMessages":[],"meta":{}}],"startTime":1773070762195,"endTime":1773070762207.1855,"status":"passed","message":"","name":"/home/vicmca/CodeProjects/School/materiais/atividades/3d-rev-01/ex04.test.js"},{"assertionResults":[{"ancestorTitles":["Exercício 05"],"fullName":"Exercício 05 ex05 - Válida - Questão 1","status":"passed","title":"ex05 - Válida - Questão 1","duration":4.836561999999958,"failureMessages":[],"meta":{}},{"ancestorTitles":["Exercício 05"],"fullName":"Exercício 05 ex05 - Correta - Questão 1","status":"passed","title":"ex05 - Correta - Questão 1","duration":1.3311459999999897,"failureMessages":[],"meta":{}},{"ancestorTitles":["Exercício 05"],"fullName":"Exercício 05 ex05 - Válida - Questão 2","status":"passed","title":"ex05 - Válida - Questão 2","duration":0.801270000000045,"failureMessages":[],"meta":{}},{"ancestorTitles":["Exercício 05"],"fullName":"Exercício 05 ex05 - Correta - Questão 2","status":"passed","title":"ex05 - Correta - Questão 2","duration":1.1340890000000172,"failureMessages":[],"meta":{}},{"ancestorTitles":["Exercício 05"],"fullName":"Exercício 05 ex05 - Válida - Questão 3","status":"passed","title":"ex05 - Válida - Questão 3","duration":0.7538920000000644,"failureMessages":[],"meta":{}},{"ancestorTitles":["Exercício 05"],"fullName":"Exercício 05 ex05 - Correta - Questão 3","status":"passed","title":"ex05 - Correta - Questão 3","duration":0.44299599999999373,"failureMessages":[],"meta":{}},{"ancestorTitles":["Exercício 05"],"fullName":"Exercício 05 ex05 - Válida - Questão 4","status":"passed","title":"ex05 - Válida - Questão 4","duration":0.7432929999999942,"failureMessages":[],"meta":{}},{"ancestorTitles":["Exercício 05"],"fullName":"Exercício 05 ex05 - Correta - Questão 4","status":"passed","title":"ex05 - Correta - Questão 4","duration":0.6198229999999967,"failureMessages":[],"meta":{}},{"ancestorTitles":["Exercício 05"],"fullName":"Exercício 05 ex05 - Válida - Questão 5","status":"passed","title":"ex05 - Válida - Questão 5","duration":1.3191289999999753,"failureMessages":[],"meta":{}},{"ancestorTitles":["Exercício 05"],"fullName":"Exercício 05 ex05 - Correta - Questão 5","status":"passed","title":"ex05 - Correta - Questão 5","duration":6.660931000000005,"failureMessages":[],"meta":{}},{"ancestorTitles":["Exercício 05"],"fullName":"Exercício 05 ex05 - Válida - Questão 6","status":"passed","title":"ex05 - Válida - Questão 6","duration":0.5136219999999412,"failureMessages":[],"meta":{}},{"ancestorTitles":["Exercício 05"],"fullName":"Exercício 05 ex05 - Correta - Questão 6","status":"failed","title":"ex05 - Correta - Questão 6","duration":27.706389999999942,"failureMessages":["AssertionError: expected false to be true // Object.is equality\n    at /home/vicmca/CodeProjects/School/materiais/atividades/3d-rev-01/ex05.test.js:17:29\n    at file:///home/vicmca/CodeProjects/School/materiais/atividades/3d-rev-01/node_modules/@vitest/runner/dist/index.js:145:11\n    at file:///home/vicmca/CodeProjects/School/materiais/atividades/3d-rev-01/node_modules/@vitest/runner/dist/index.js:915:26\n    at file:///home/vicmca/CodeProjects/School/materiais/atividades/3d-rev-01/node_modules/@vitest/runner/dist/index.js:1243:20\n    at new Promise (<anonymous>)\n    at runWithTimeout (file:///home/vicmca/CodeProjects/School/materiais/atividades/3d-rev-01/node_modules/@vitest/runner/dist/index.js:1209:10)\n    at file:///home/vicmca/CodeProjects/School/materiais/atividades/3d-rev-01/node_modules/@vitest/runner/dist/index.js:1653:37\n    at Traces.$ (file:///home/vicmca/CodeProjects/School/materiais/atividades/3d-rev-01/node_modules/vitest/dist/chunks/traces.CCmnQaNT.js:142:27)\n    at trace (file:///home/vicmca/CodeProjects/School/materiais/atividades/3d-rev-01/node_modules/vitest/dist/chunks/test.B8ej_ZHS.js:239:21)\n    at runTest (file:///home/vicmca/CodeProjects/School/materiais/atividades/3d-rev-01/node_modules/@vitest/runner/dist/index.js:1653:12)"],"meta":{}},{"ancestorTitles":["Exercício 05"],"fullName":"Exercício 05 ex05 - Válida - Questão 7","status":"passed","title":"ex05 - Válida - Questão 7","duration":0.46502200000009,"failureMessages":[],"meta":{}},{"ancestorTitles":["Exercício 05"],"fullName":"Exercício 05 ex05 - Correta - Questão 7","status":"passed","title":"ex05 - Correta - Questão 7","duration":0.31467800000007173,"failureMessages":[],"meta":{}},{"ancestorTitles":["Exercício 05"],"fullName":"Exercício 05 ex05 - Válida - Questão 8","status":"passed","title":"ex05 - Válida - Questão 8","duration":0.4305810000000747,"failureMessages":[],"meta":{}},{"ancestorTitles":["Exercício 05"],"fullName":"Exercício 05 ex05 - Correta - Questão 8","status":"passed","title":"ex05 - Correta - Questão 8","duration":0.3414390000000367,"failureMessages":[],"meta":{}},{"ancestorTitles":["Exercício 05"],"fullName":"Exercício 05 ex05 - Válida - Questão 9","status":"passed","title":"ex05 - Válida - Questão 9","duration":0.4210839999999507,"failureMessages":[],"meta":{}},{"ancestorTitles":["Exercício 05"],"fullName":"Exercício 05 ex05 - Correta - Questão 9","status":"passed","title":"ex05 - Correta - Questão 9","duration":0.3620420000000877,"failureMessages":[],"meta":{}},{"ancestorTitles":["Exercício 05"],"fullName":"Exercício 05 ex05 - Válida - Questão 10","status":"passed","title":"ex05 - Válida - Questão 10","duration":0.43240099999991344,"failureMessages":[],"meta":{}},{"ancestorTitles":["Exercício 05"],"fullName":"Exercício 05 ex05 - Correta - Questão 10","status":"passed","title":"ex05 - Correta - Questão 10","duration":0.38233600000000934,"failureMessages":[],"meta":{}}],"startTime":1773070761519,"endTime":1773070761571.3823,"status":"failed","message":"","name":"/home/vicmca/CodeProjects/School/materiais/atividades/3d-rev-01/ex05.test.js"}]}